shovel/CLAUDE.md
shovel/README.md
shovel/.claude/settings.json
shovel/.claude/commands/build.md
shovel/.claude/commands/c-level.md
shovel/.claude/commands/check-complete.md
shovel/.claude/commands/commit.md
shovel/.claude/commands/deep-debug.md
shovel/.claude/commands/design.md
shovel/.claude/commands/error-log.md
shovel/.claude/commands/gate.md
shovel/.claude/commands/handoff.md
shovel/.claude/commands/implement.md
shovel/.claude/commands/interview.md
shovel/.claude/commands/learn-error.md
shovel/.claude/commands/lint.md
shovel/.claude/commands/plan.md
shovel/.claude/commands/pm.md
shovel/.claude/commands/review.md
shovel/.claude/commands/ssot-check.md
shovel/.claude/commands/start.md
shovel/.claude/commands/step-done.md
shovel/.claude/commands/sync.md
shovel/.claude/commands/test.md
shovel/.claude/commands/typecheck.md
shovel/.claude/commands/verify-server.md
shovel/.claude/commands/verify.md
shovel/.claude/config/roles.yaml
shovel/.claude/evidence/.gitkeep
shovel/.claude/logs/.gitkeep
shovel/.claude/plans/.gitkeep
shovel/.claude/templates/PRD.template.md
shovel/.claude/templates/api.claude.md
shovel/.claude/templates/c-level-response.md
shovel/.claude/templates/desktop.claude.md
shovel/.claude/templates/findings.template.md
shovel/.claude/templates/fullstack.claude.md
shovel/.claude/templates/web.claude.md
shovel/scripts/gate.sh
shovel/scripts/parallel-terminals.ps1
shovel/scripts/parallel-terminals.sh
shovel/scripts/parallel-web.sh
shovel/scripts/start-parallel.sh
clouvel_pro/__init__.py
clouvel_pro/content_api.py
clouvel_pro/license.py
clouvel_pro/server.py
clouvel_pro/tools/__init__.py
clouvel_pro/tools/context.py
clouvel_pro/tools/errors.py
clouvel_pro/tools/hooks.py
clouvel_pro/tools/shovel.py
clouvel_pro/tools/team.py
clouvel_pro-2.0.0.dist-info/METADATA
clouvel_pro-2.0.0.dist-info/WHEEL
clouvel_pro-2.0.0.dist-info/entry_points.txt
clouvel_pro-2.0.0.dist-info/licenses/LICENSE
clouvel_pro-2.0.0.dist-info/RECORD
