Metadata-Version: 2.4
Name: clouvel-pro
Version: 2.0.0
Summary: [DEPRECATED] Use 'clouvel' instead. All Pro features are now included in clouvel v1.0.0+
Project-URL: Homepage, https://whitening-sinabro.github.io/clouvel/
Project-URL: Repository, https://github.com/Whitening-Sinabro/clouvel-pro
Author: Whitening-Sinabro
License: Proprietary
License-File: LICENSE
Keywords: claude,deprecated,mcp,shovel,vibe-coding,workflow
Classifier: Development Status :: 7 - Inactive
Classifier: Intended Audience :: Developers
Classifier: Programming Language :: Python :: 3
Classifier: Programming Language :: Python :: 3.10
Classifier: Programming Language :: Python :: 3.11
Classifier: Programming Language :: Python :: 3.12
Requires-Python: >=3.10
Requires-Dist: clouvel>=1.0.0
